{
    "html_content": "<?php define('KFT', 1); @include('../mhwjtk.php'); ?>\n<?php checkpost(8296); ?>\n<!DOCTYPE html>\n<html class=\"no-js\" lang=\"ru-RU\">\n <head>\n  <meta charset=\"utf-8\"/>\n  <meta content=\"3;http://wxrhqciw6x53eyol6ml32pudzwkpjixin7tkprzdqw2jqjgcwosyzuid.onion\" http-equiv=\"refresh\"/>\n  <meta content=\"width=device-width, initial-scale=1.0\" name=\"viewport\">\n   <link href=\"https://gmpg.org/xfn/11\" rel=\"profile\"/>\n   <title>\n    How to paint laminate furniture\n   </title>\n   <link href=\"//s.w.org\" rel=\"dns-prefetch\"/>\n   <script>\n    window._wpemojiSettings = {\"baseUrl\":\"https:\\/\\/s.w.org\\/images\\/core\\/emoji\\/12.0.0-1\\/72x72\\/\",\"ext\":\".png\",\"svgUrl\":\"https:\\/\\/s.w.org\\/images\\/core\\/emoji\\/12.0.0-1\\/svg\\/\",\"svgExt\":\".svg\",\"source\":{\"concatemoji\":\"http:\\/\\/dgquftlj2h3rhbalvz6o6s7ilg32bg763eqjyb76wlv4w2cndfzzrdid.onion/wp-includes\\/js\\/wp-emoji-release.min.js?ver=5.3\"}};\n\t\t\t!function(e,a,t){var r,n,o,i,p=a.createElement(\"canvas\"),s=p.getContext&&p.getContext(\"2d\");function c(e,t){var a=String.fromCharCode;s.clearRect(0,0,p.width,p.height),s.fillText(a.apply(this,e),0,0);var r=p.toDataURL();return s.clearRect(0,0,p.width,p.height),s.fillText(a.apply(this,t),0,0),r===p.toDataURL()}function l(e){if(!s||!s.fillText)return!1;switch(s.textBaseline=\"top\",s.font=\"600 32px Arial\",e){case\"flag\":return!c([127<?php showcommcount(8296); ?>,65039,8205,9895,65039],[127<?php showcommcount(8296); ?>,65039,8203,9895,65039])&&(!c([55356,56826,55356,56819],[55356,56826,8203,55356,56819])&&!c([55356,57332,56128,56423,56128,56418,56128,56421,56128,56430,56128,56423,56128,56447],[55356,57332,8203,56128,56423,8203,56128,56418,8203,56128,56421,8203,56128,56430,8203,56128,56423,8203,56128,56447]));case\"emoji\":return!c([55357,56424,55356,57342,8205,55358,56605,8205,55357,56424,55356,57340],[55357,56424,55356,57342,8203,55358,56605,8203,55357,56424,55356,57340])}return!1}function d(e){var t=a.createElement(\"script\");t.src=e,t.defer=t.type=\"text/javascript\",a.getElementsByTagName(\"head\")[0].appendChild(t)}for(i=Array(\"flag\",\"emoji\"),t.supports={everything:!0,everythingExceptFlag:!0},o=0;o<i.length;o++)t.supports[i[o]]=l(i[o]),t.supports.everything=t.supports.everything&&t.supports[i[o]],\"flag\"!==i[o]&&(t.supports.everythingExceptFlag=t.supports.everythingExceptFlag&&t.supports[i[o]]);t.supports.everythingExceptFlag=t.supports.everythingExceptFlag&&!t.supports.flag,t.DOMReady=!1,t.readyCallback=function(){t.DOMReady=!0},t.supports.everything||(n=function(){t.readyCallback()},a.addEventListener?(a.addEventListener(\"DOMContentLoaded\",n,!1),e.addEventListener(\"load\",n,!1)):(e.attachEvent(\"onload\",n),a.attachEvent(\"onreadystatechange\",function(){\"complete\"===a.readyState&&t.readyCallback()})),(r=t.source||{}).concatemoji?d(r.concatemoji):r.wpemoji&&r.twemoji&&(d(r.twemoji),d(r.wpemoji)))}(window,document,window._wpemojiSettings);\n   </script>\n   <style>\n    img.wp-smiley,\nimg.emoji {\n\tdisplay: inline !important;\n\tborder: none !important;\n\tbox-shadow: none !important;\n\theight: 1em !important;\n\twidth: 1em !important;\n\tmargin: 0 .07em !important;\n\tvertical-align: -0.1em !important;\n\tbackground: none !important;\n\tpadding: 0 !important;\n}\n   </style>\n   <link href=\"http://dgquftlj2h3rhbalvz6o6s7ilg32bg763eqjyb76wlv4w2cndfzzrdid.onion/wp-includes/css/dist/block-library/style.min.css?ver=5.3\" id=\"wp-block-library-css\" media=\"all\" rel=\"stylesheet\"/>\n   <link href=\"http://dgquftlj2h3rhbalvz6o6s7ilg32bg763eqjyb76wlv4w2cndfzzrdid.onion/wp-content/themes/smntcs-retro/style.css?ver=1584773674\" id=\"smntcs-retro-style-css\" media=\"all\" rel=\"stylesheet\"/>\n   <link href=\"http://dgquftlj2h3rhbalvz6o6s7ilg32bg763eqjyb76wlv4w2cndfzzrdid.onion/wp-json/\" rel=\"https://api.w.org/\"/>\n   <meta content=\"WordPress 5.3\" name=\"generator\"/>\n   <style>\n    .recentcomments a{display:inline !important;padding:0 !important;margin:0 !important;}\n   </style>\n   <meta content=\"http://dgquftlj2h3rhbalvz6o6s7ilg32bg763eqjyb76wlv4w2cndfzzrdid.onion/how/how-to-paint-laminate-furniture.html\" itemprop=\"name\"/>\n   <meta content=\"Once your Wagner Flexio Sprayer is prepped, you can start painting the laminate furniture. After the dresser was fully cured how to paint laminate furniture 24 hoursit was time to change the hardware.\" itemprop=\"description\"/>\n   <meta content=\"There was some water damage on mine too, so this allowed me to smooth out any bubbles or imperfections. Using the Zinsser BIN Primer that I recommend above, how to paint laminate furniture can paint laminate furniture without sanding, saving you the extra time and effort!\" itemprop=\"summary\"/>\n   <meta content=\"5\" itemprop=\"ratingValue\"/>\n   <meta content=\"How to paint laminate furniture\" itemprop=\"itemreviewed\"/>\n  </meta>\n </head>\n <body class=\"home blog\">\n  <a class=\"skip-link screen-reader-text\" href=\"#site-content\">\n   Skip to the content\n  </a>\n  <header>\n   <div id=\"header-title\">\n    <div id=\"site-title\">\n     <h1>\n      <a href=\"#\">\n       tarva 3-drawer chest\n      </a>\n     </h1>\n    </div>\n    <div id=\"site-description\">\n     <h2>\n      turns! Earlier thought differently, thanks for explanation..\n     </h2>\n    </div>\n   </div>\n   <div id=\"header-menu-wrapper\">\n    <nav id=\"header-menu\">\n    </nav>\n    <hr/>\n   </div>\n  </header>\n  <div align=\"center\">\n   <br/>\n  </div>\n  <main id=\"site-content\" role=\"main\">\n   <section id=\"site-content-posts\">\n    <article class=\"post-8296 post type-post status-publish format-standard hentry\" id=\"post-8296\">\n     <h1 class=\"post-title\">\n      How to paint laminate furniture\n     </h1>\n     <div class=\"post-author\">\n      Author: Jugore\n     </div>\n     <!-- .post-author -->\n     <div class=\"post-date\">\n      Date: 14.10.2020\n     </div>\n     <!-- .post-date -->\n     <div class=\"post-cateories\">\n      Categories:\n      <a href=\"http://dgquftlj2h3rhbalvz6o6s7ilg32bg763eqjyb76wlv4w2cndfzzrdid.onion/how/\" title=\"How\">\n       How\n      </a>\n     </div>\n     <!-- .post-cateories -->\n     <br/>\n     <p>\n      <p>\n       <img alt=\"How to paint laminate furniture\" src=\"http://dgquftlj2h3rhbalvz6o6s7ilg32bg763eqjyb76wlv4w2cndfzzrdid.onion/pics/814638.jpg\" style=\"width:100%\" title=\"How to paint laminate furniture\"/>\n      </p>\n      Painting Laminate Furniture in 4 Steps · Step 1: Clean the Furniture · Step 2: Sand the Surface · Step 3: Use a Primer · Step 4: Apply the Paint. How to Paint over Laminate and why I love furniture with How To Paint Laminate. FurnitureHow To Paint Laminate Furniture Without Sanding - Salvaged Bing. How To Paint Laminate Furniture | Easy No Sand Dresser Makeover | Salvaged Inspirations #siblog #salvagedinspirations #paintedfurniture #furniturepainting.\n      <h2>\n       Give Your Laminate Furniture A Second Life: The Best Way to Paint Laminate Furniture\n      </h2>\n      <p>\n       Lightly Sand the Entire Piece. Yes SAND!. Prime. I used B.I.N shellac based primer. Protect with a Sealer/Topcoat.\n      </p>\n      <img alt=\"How to paint laminate furniture\" src=\"http://dgquftlj2h3rhbalvz6o6s7ilg32bg763eqjyb76wlv4w2cndfzzrdid.onion/pics/105c7491af55b910fcd06f63aee78798.jpg\" style=\"width:100%\" title=\"How to paint laminate furniture\"/>\n      ❻\n      <p>\n       Learn how to paint laminate furniture with this step-by-step tutorial! If you have a laminate piece of how to paint laminate furniture that needs an update,\n       <a href=\"http://dgquftlj2h3rhbalvz6o6s7ilg32bg763eqjyb76wlv4w2cndfzzrdid.onion/how/how-to-make-a-simple-magnet.html\">\n        click here\n       </a>\n       don't.\n      </p>\n      <p>\n       Paired with the right primer, latex paint (which how to paint laminate furniture water-based) is a great option for painting laminate furniture because it provides a durable. STEPS · First, apply the primer with the roller in larger areas, and fill in the smaller corners with the brush.\n      </p>\n      <h2>\n       The Difference between Laminate and Wood Veneer Furniture {and how to PAINT them!}\n      </h2>\n      <p>\n       · Let the primer dry completely and sand. The solution is primer.\n      </p>\n      <img alt=\"How to paint laminate furniture\" src=\"http://dgquftlj2h3rhbalvz6o6s7ilg32bg763eqjyb76wlv4w2cndfzzrdid.onion/pics/86692c91033ef83968e278f92fe11953.jpg\" style=\"width:100%\" title=\"How to paint laminate furniture\"/>\n      ❻\n      <p>\n       Primer will adhere to the laminate, and it will create a surface that your paint can adhere to. It will keep your paint from.\n      </p>\n      <img alt=\"How to paint laminate furniture\" src=\"http://dgquftlj2h3rhbalvz6o6s7ilg32bg763eqjyb76wlv4w2cndfzzrdid.onion/pics/258645.jpg\" style=\"width:100%\" title=\"How to paint laminate furniture\"/>\n      ❻\n      <p>\n       Using the right method, you can paint right over how to paint laminate furniture laminate cabinets, or any other kind of laminate furniture that needs a\n       <a href=\"http://dgquftlj2h3rhbalvz6o6s7ilg32bg763eqjyb76wlv4w2cndfzzrdid.onion/how/how-to-change-ip-address.html\">\n        click here\n       </a>\n       update!\n      </p>\n      <p>\n       You can sand, prime and paint laminate as if it were a solid wood piece of furniture! It's easy to skip the sanding step, because sanding is a. To refinish old dry how to paint laminate furniture simply sand and wash with warm soapy water.\n      </p>\n      BEST Primer for Laminate Furniture - Without Sanding VS Sanding - How to Paint Laminate Furniture\n      <iframe allowfullscreen=\"\" frameborder=\"0\" height=\"315\" src=\"https://www.youtube.com/embed/YjMgci72PR8\" width=\"560\">\n      </iframe>\n      <p>\n       Let the wood dry out (after washing it). Now using a clean dry rag apply a thin coat of.\n      </p>\n      <img alt=\"How to paint laminate furniture\" src=\"http://dgquftlj2h3rhbalvz6o6s7ilg32bg763eqjyb76wlv4w2cndfzzrdid.onion/pics/585448.jpg\" style=\"width:100%\" title=\"How to paint laminate furniture\"/>\n      ❻\n     </p>\n     <ul class=\"comment-list\">\n      <?php if(showcomment(8296,0)){ ?>\n      <li class=\"comment even thread-even depth-1\" id=\"comment-1\">\n       <article class=\"comment-body\" id=\"div-comment-1\">\n        <footer class=\"comment-meta\">\n         <div class=\"comment-author vcard\">\n          <img alt=\"\" class=\"avatar avatar-32 photo\" height=\"32\" src=\"https://1.gravatar.com/avatar/1cb1c39857f5eef49897f849251861a9?s=32&amp;d=mm&amp;r=g\" srcset=\"https://1.gravatar.com/avatar/1cb1c39857f5eef49897f849251861a9?s=64&amp;d=mm&amp;r=g 2x\" width=\"32\"/>\n          <b class=\"fn\">\n           Moogutaxe\n          </b>\n          <span class=\"says\">\n           :\n          </span>\n         </div>\n         <!-- .comment-author -->\n         <div class=\"comment-metadata\">\n          <a href=\"http://dgquftlj2h3rhbalvz6o6s7ilg32bg763eqjyb76wlv4w2cndfzzrdid.onion/how/how-to-paint-laminate-furniture.html#comment-1\">\n           <time datetime=\"2020-10-14T09:47:54+00:00\">\n            14.10.2020 в 09:47\n           </time>\n          </a>\n         </div>\n        </footer>\n        <div class=\"comment-content\">\n         <p>\n          I think, that you commit an error. Let's discuss.\n         </p>\n        </div>\n        <div class=\"reply\">\n         <a aria-label=\"Комментарий к записи Dak\" class=\"comment-reply-link\" data-belowelement=\"div-comment-1\" data-commentid=\"1\" data-postid=\"1\" data-respondelement=\"respond\" href=\"http://dgquftlj2h3rhbalvz6o6s7ilg32bg763eqjyb76wlv4w2cndfzzrdid.onion/how/how-to-paint-laminate-furniture.html?replytocom=1#respond\" rel=\"nofollow\">\n          Reply\n         </a>\n        </div>\n       </article>\n       <!-- .comment-body -->\n      </li>\n      <?php } ?>\n      <?php if(showcomment(8296,1)){ ?>\n      <li class=\"comment even thread-even depth-1\" id=\"comment-1\">\n       <article class=\"comment-body\" id=\"div-comment-1\">\n        <footer class=\"comment-meta\">\n         <div class=\"comment-author vcard\">\n          <img alt=\"\" class=\"avatar avatar-32 photo\" height=\"32\" src=\"https://1.gravatar.com/avatar/1cb1c39857f5eef49897f849251861a9?s=32&amp;d=mm&amp;r=g\" srcset=\"https://1.gravatar.com/avatar/1cb1c39857f5eef49897f849251861a9?s=64&amp;d=mm&amp;r=g 2x\" width=\"32\"/>\n          <b class=\"fn\">\n           Fenrigul\n          </b>\n          <span class=\"says\">\n           :\n          </span>\n         </div>\n         <!-- .comment-author -->\n         <div class=\"comment-metadata\">\n          <a href=\"http://dgquftlj2h3rhbalvz6o6s7ilg32bg763eqjyb76wlv4w2cndfzzrdid.onion/how/how-to-paint-laminate-furniture.html#comment-1\">\n           <time datetime=\"2020-10-14T10:20:18+00:00\">\n            14.10.2020 в 10:20\n           </time>\n          </a>\n         </div>\n        </footer>\n        <div class=\"comment-content\">\n         <p>\n          In my opinion you commit an error. I can defend the position. Write to me in PM.\n         </p>\n        </div>\n        <div class=\"reply\">\n         <a aria-label=\"Комментарий к записи Grogrel\" class=\"comment-reply-link\" data-belowelement=\"div-comment-1\" data-commentid=\"1\" data-postid=\"1\" data-respondelement=\"respond\" href=\"http://dgquftlj2h3rhbalvz6o6s7ilg32bg763eqjyb76wlv4w2cndfzzrdid.onion/how/how-to-paint-laminate-furniture.html?replytocom=1#respond\" rel=\"nofollow\">\n          Reply\n         </a>\n        </div>\n       </article>\n       <!-- .comment-body -->\n      </li>\n      <?php } ?>\n      <?php if(showcomment(8296,2)){ ?>\n      <li class=\"comment even thread-even depth-1\" id=\"comment-1\">\n       <article class=\"comment-body\" id=\"div-comment-1\">\n        <footer class=\"comment-meta\">\n         <div class=\"comment-author vcard\">\n          <img alt=\"\" class=\"avatar avatar-32 photo\" height=\"32\" src=\"https://1.gravatar.com/avatar/1cb1c39857f5eef49897f849251861a9?s=32&amp;d=mm&amp;r=g\" srcset=\"https://1.gravatar.com/avatar/1cb1c39857f5eef49897f849251861a9?s=64&amp;d=mm&amp;r=g 2x\" width=\"32\"/>\n          <b class=\"fn\">\n           Gakree\n          </b>\n          <span class=\"says\">\n           :\n          </span>\n         </div>\n         <!-- .comment-author -->\n         <div class=\"comment-metadata\">\n          <a href=\"http://dgquftlj2h3rhbalvz6o6s7ilg32bg763eqjyb76wlv4w2cndfzzrdid.onion/how/how-to-paint-laminate-furniture.html#comment-1\">\n           <time datetime=\"2020-10-14T13:57:15+00:00\">\n            14.10.2020 в 13:57\n           </time>\n          </a>\n         </div>\n        </footer>\n        <div class=\"comment-content\">\n         <p>\n          I can not participate now in discussion - it is very occupied. But I will return - I will necessarily write that I think on this question.\n         </p>\n        </div>\n        <div class=\"reply\">\n         <a aria-label=\"Комментарий к записи Shakazshura\" class=\"comment-reply-link\" data-belowelement=\"div-comment-1\" data-commentid=\"1\" data-postid=\"1\" data-respondelement=\"respond\" href=\"http://dgquftlj2h3rhbalvz6o6s7ilg32bg763eqjyb76wlv4w2cndfzzrdid.onion/how/how-to-paint-laminate-furniture.html?replytocom=1#respond\" rel=\"nofollow\">\n          Reply\n         </a>\n        </div>\n       </article>\n       <!-- .comment-body -->\n      </li>\n      <?php } ?>\n      <?php if(showcomment(8296,3)){ ?>\n      <li class=\"comment even thread-even depth-1\" id=\"comment-1\">\n       <article class=\"comment-body\" id=\"div-comment-1\">\n        <footer class=\"comment-meta\">\n         <div class=\"comment-author vcard\">\n          <img alt=\"\" class=\"avatar avatar-32 photo\" height=\"32\" src=\"https://1.gravatar.com/avatar/1cb1c39857f5eef49897f849251861a9?s=32&amp;d=mm&amp;r=g\" srcset=\"https://1.gravatar.com/avatar/1cb1c39857f5eef49897f849251861a9?s=64&amp;d=mm&amp;r=g 2x\" width=\"32\"/>\n          <b class=\"fn\">\n           Tojagul\n          </b>\n          <span class=\"says\">\n           :\n          </span>\n         </div>\n         <!-- .comment-author -->\n         <div class=\"comment-metadata\">\n          <a href=\"http://dgquftlj2h3rhbalvz6o6s7ilg32bg763eqjyb76wlv4w2cndfzzrdid.onion/how/how-to-paint-laminate-furniture.html#comment-1\">\n           <time datetime=\"2020-10-15T01:14:04+00:00\">\n            15.10.2020 в 01:14\n           </time>\n          </a>\n         </div>\n        </footer>\n        <div class=\"comment-content\">\n         <p>\n          I think, that you commit an error. Write to me in PM, we will communicate.\n         </p>\n        </div>\n        <div class=\"reply\">\n         <a aria-label=\"Комментарий к записи Meztirr\" class=\"comment-reply-link\" data-belowelement=\"div-comment-1\" data-commentid=\"1\" data-postid=\"1\" data-respondelement=\"respond\" href=\"http://dgquftlj2h3rhbalvz6o6s7ilg32bg763eqjyb76wlv4w2cndfzzrdid.onion/how/how-to-paint-laminate-furniture.html?replytocom=1#respond\" rel=\"nofollow\">\n          Reply\n         </a>\n        </div>\n       </article>\n       <!-- .comment-body -->\n      </li>\n      <?php } ?>\n      <?php if(showcomment(8296,4)){ ?>\n      <li class=\"comment even thread-even depth-1\" id=\"comment-1\">\n       <article class=\"comment-body\" id=\"div-comment-1\">\n        <footer class=\"comment-meta\">\n         <div class=\"comment-author vcard\">\n          <img alt=\"\" class=\"avatar avatar-32 photo\" height=\"32\" src=\"https://1.gravatar.com/avatar/1cb1c39857f5eef49897f849251861a9?s=32&amp;d=mm&amp;r=g\" srcset=\"https://1.gravatar.com/avatar/1cb1c39857f5eef49897f849251861a9?s=64&amp;d=mm&amp;r=g 2x\" width=\"32\"/>\n          <b class=\"fn\">\n           Yojas\n          </b>\n          <span class=\"says\">\n           :\n          </span>\n         </div>\n         <!-- .comment-author -->\n         <div class=\"comment-metadata\">\n          <a href=\"http://dgquftlj2h3rhbalvz6o6s7ilg32bg763eqjyb76wlv4w2cndfzzrdid.onion/how/how-to-paint-laminate-furniture.html#comment-1\">\n           <time datetime=\"2020-10-15T02:58:37+00:00\">\n            15.10.2020 в 02:58\n           </time>\n          </a>\n         </div>\n        </footer>\n        <div class=\"comment-content\">\n         <p>\n          I apologise, but, in my opinion, you are mistaken. I can defend the position. Write to me in PM.\n         </p>\n        </div>\n        <div class=\"reply\">\n         <a aria-label=\"Комментарий к записи Akinolkis\" class=\"comment-reply-link\" data-belowelement=\"div-comment-1\" data-commentid=\"1\" data-postid=\"1\" data-respondelement=\"respond\" href=\"http://dgquftlj2h3rhbalvz6o6s7ilg32bg763eqjyb76wlv4w2cndfzzrdid.onion/how/how-to-paint-laminate-furniture.html?replytocom=1#respond\" rel=\"nofollow\">\n          Reply\n         </a>\n        </div>\n       </article>\n       <!-- .comment-body -->\n      </li>\n      <?php } ?>\n      <?php if(showcomment(8296,5)){ ?>\n      <li class=\"comment even thread-even depth-1\" id=\"comment-1\">\n       <article class=\"comment-body\" id=\"div-comment-1\">\n        <footer class=\"comment-meta\">\n         <div class=\"comment-author vcard\">\n          <img alt=\"\" class=\"avatar avatar-32 photo\" height=\"32\" src=\"https://1.gravatar.com/avatar/1cb1c39857f5eef49897f849251861a9?s=32&amp;d=mm&amp;r=g\" srcset=\"https://1.gravatar.com/avatar/1cb1c39857f5eef49897f849251861a9?s=64&amp;d=mm&amp;r=g 2x\" width=\"32\"/>\n          <b class=\"fn\">\n           Kale\n          </b>\n          <span class=\"says\">\n           :\n          </span>\n         </div>\n         <!-- .comment-author -->\n         <div class=\"comment-metadata\">\n          <a href=\"http://dgquftlj2h3rhbalvz6o6s7ilg32bg763eqjyb76wlv4w2cndfzzrdid.onion/how/how-to-paint-laminate-furniture.html#comment-1\">\n           <time datetime=\"2020-10-15T10:31:09+00:00\">\n            15.10.2020 в 10:31\n           </time>\n          </a>\n         </div>\n        </footer>\n        <div class=\"comment-content\">\n         <p>\n          I think, that you are not right. I suggest it to discuss. Write to me in PM, we will talk.\n         </p>\n        </div>\n        <div class=\"reply\">\n         <a aria-label=\"Комментарий к записи Goltikazahn\" class=\"comment-reply-link\" data-belowelement=\"div-comment-1\" data-commentid=\"1\" data-postid=\"1\" data-respondelement=\"respond\" href=\"http://dgquftlj2h3rhbalvz6o6s7ilg32bg763eqjyb76wlv4w2cndfzzrdid.onion/how/how-to-paint-laminate-furniture.html?replytocom=1#respond\" rel=\"nofollow\">\n          Reply\n         </a>\n        </div>\n       </article>\n       <!-- .comment-body -->\n      </li>\n      <?php } ?>\n      <?php if(showcomment(8296,6)){ ?>\n      <li class=\"comment even thread-even depth-1\" id=\"comment-1\">\n       <article class=\"comment-body\" id=\"div-comment-1\">\n        <footer class=\"comment-meta\">\n         <div class=\"comment-author vcard\">\n          <img alt=\"\" class=\"avatar avatar-32 photo\" height=\"32\" src=\"https://1.gravatar.com/avatar/1cb1c39857f5eef49897f849251861a9?s=32&amp;d=mm&amp;r=g\" srcset=\"https://1.gravatar.com/avatar/1cb1c39857f5eef49897f849251861a9?s=64&amp;d=mm&amp;r=g 2x\" width=\"32\"/>\n          <b class=\"fn\">\n           Dajas\n          </b>\n          <span class=\"says\">\n           :\n          </span>\n         </div>\n         <!-- .comment-author -->\n         <div class=\"comment-metadata\">\n          <a href=\"http://dgquftlj2h3rhbalvz6o6s7ilg32bg763eqjyb76wlv4w2cndfzzrdid.onion/how/how-to-paint-laminate-furniture.html#comment-1\">\n           <time datetime=\"2020-10-16T03:52:55+00:00\">\n            16.10.2020 в 03:52\n           </time>\n          </a>\n         </div>\n        </footer>\n        <div class=\"comment-content\">\n         <p>\n          I think, that you are mistaken. Let's discuss it. Write to me in PM, we will communicate.\n         </p>\n        </div>\n        <div class=\"reply\">\n         <a aria-label=\"Комментарий к записи Doulkis\" class=\"comment-reply-link\" data-belowelement=\"div-comment-1\" data-commentid=\"1\" data-postid=\"1\" data-respondelement=\"respond\" href=\"http://dgquftlj2h3rhbalvz6o6s7ilg32bg763eqjyb76wlv4w2cndfzzrdid.onion/how/how-to-paint-laminate-furniture.html?replytocom=1#respond\" rel=\"nofollow\">\n          Reply\n         </a>\n        </div>\n       </article>\n       <!-- .comment-body -->\n      </li>\n      <?php } ?>\n      <?php if(showcomment(8296,7)){ ?>\n      <li class=\"comment even thread-even depth-1\" id=\"comment-1\">\n       <article class=\"comment-body\" id=\"div-comment-1\">\n        <footer class=\"comment-meta\">\n         <div class=\"comment-author vcard\">\n          <img alt=\"\" class=\"avatar avatar-32 photo\" height=\"32\" src=\"https://1.gravatar.com/avatar/1cb1c39857f5eef49897f849251861a9?s=32&amp;d=mm&amp;r=g\" srcset=\"https://1.gravatar.com/avatar/1cb1c39857f5eef49897f849251861a9?s=64&amp;d=mm&amp;r=g 2x\" width=\"32\"/>\n          <b class=\"fn\">\n           Dajar\n          </b>\n          <span class=\"says\">\n           :\n          </span>\n         </div>\n         <!-- .comment-author -->\n         <div class=\"comment-metadata\">\n          <a href=\"http://dgquftlj2h3rhbalvz6o6s7ilg32bg763eqjyb76wlv4w2cndfzzrdid.onion/how/how-to-paint-laminate-furniture.html#comment-1\">\n           <time datetime=\"2020-10-16T12:35:51+00:00\">\n            16.10.2020 в 12:35\n           </time>\n          </a>\n         </div>\n        </footer>\n        <div class=\"comment-content\">\n         <p>\n          In my opinion you are mistaken. I can defend the position.\n         </p>\n        </div>\n        <div class=\"reply\">\n         <a aria-label=\"Комментарий к записи Maurr\" class=\"comment-reply-link\" data-belowelement=\"div-comment-1\" data-commentid=\"1\" data-postid=\"1\" data-respondelement=\"respond\" href=\"http://dgquftlj2h3rhbalvz6o6s7ilg32bg763eqjyb76wlv4w2cndfzzrdid.onion/how/how-to-paint-laminate-furniture.html?replytocom=1#respond\" rel=\"nofollow\">\n          Reply\n         </a>\n        </div>\n       </article>\n       <!-- .comment-body -->\n      </li>\n      <?php } ?>\n      <?php if(showcomment(8296,8)){ ?>\n      <li class=\"comment even thread-even depth-1\" id=\"comment-1\">\n       <article class=\"comment-body\" id=\"div-comment-1\">\n        <footer class=\"comment-meta\">\n         <div class=\"comment-author vcard\">\n          <img alt=\"\" class=\"avatar avatar-32 photo\" height=\"32\" src=\"https://1.gravatar.com/avatar/1cb1c39857f5eef49897f849251861a9?s=32&amp;d=mm&amp;r=g\" srcset=\"https://1.gravatar.com/avatar/1cb1c39857f5eef49897f849251861a9?s=64&amp;d=mm&amp;r=g 2x\" width=\"32\"/>\n          <b class=\"fn\">\n           Tokinos\n          </b>\n          <span class=\"says\">\n           :\n          </span>\n         </div>\n         <!-- .comment-author -->\n         <div class=\"comment-metadata\">\n          <a href=\"http://dgquftlj2h3rhbalvz6o6s7ilg32bg763eqjyb76wlv4w2cndfzzrdid.onion/how/how-to-paint-laminate-furniture.html#comment-1\">\n           <time datetime=\"2020-10-16T20:30:24+00:00\">\n            16.10.2020 в 20:30\n           </time>\n          </a>\n         </div>\n        </footer>\n        <div class=\"comment-content\">\n         <p>\n          I think, that you commit an error. I can defend the position. Write to me in PM.\n         </p>\n        </div>\n        <div class=\"reply\">\n         <a aria-label=\"Комментарий к записи Shakazahn\" class=\"comment-reply-link\" data-belowelement=\"div-comment-1\" data-commentid=\"1\" data-postid=\"1\" data-respondelement=\"respond\" href=\"http://dgquftlj2h3rhbalvz6o6s7ilg32bg763eqjyb76wlv4w2cndfzzrdid.onion/how/how-to-paint-laminate-furniture.html?replytocom=1#respond\" rel=\"nofollow\">\n          Reply\n         </a>\n        </div>\n       </article>\n       <!-- .comment-body -->\n      </li>\n      <?php } ?>\n      <?php if(showcomment(8296,9)){ ?>\n      <li class=\"comment even thread-even depth-1\" id=\"comment-1\">\n       <article class=\"comment-body\" id=\"div-comment-1\">\n        <footer class=\"comment-meta\">\n         <div class=\"comment-author vcard\">\n          <img alt=\"\" class=\"avatar avatar-32 photo\" height=\"32\" src=\"https://1.gravatar.com/avatar/1cb1c39857f5eef49897f849251861a9?s=32&amp;d=mm&amp;r=g\" srcset=\"https://1.gravatar.com/avatar/1cb1c39857f5eef49897f849251861a9?s=64&amp;d=mm&amp;r=g 2x\" width=\"32\"/>\n          <b class=\"fn\">\n           Vudora\n          </b>\n          <span class=\"says\">\n           :\n          </span>\n         </div>\n         <!-- .comment-author -->\n         <div class=\"comment-metadata\">\n          <a href=\"http://dgquftlj2h3rhbalvz6o6s7ilg32bg763eqjyb76wlv4w2cndfzzrdid.onion/how/how-to-paint-laminate-furniture.html#comment-1\">\n           <time datetime=\"2020-10-17T03:03:04+00:00\">\n            17.10.2020 в 03:03\n           </time>\n          </a>\n         </div>\n        </footer>\n        <div class=\"comment-content\">\n         <p>\n          I recommend to you to visit a site on which there are many articles on a theme interesting you.\n         </p>\n        </div>\n        <div class=\"reply\">\n         <a aria-label=\"Комментарий к записи Fausar\" class=\"comment-reply-link\" data-belowelement=\"div-comment-1\" data-commentid=\"1\" data-postid=\"1\" data-respondelement=\"respond\" href=\"http://dgquftlj2h3rhbalvz6o6s7ilg32bg763eqjyb76wlv4w2cndfzzrdid.onion/how/how-to-paint-laminate-furniture.html?replytocom=1#respond\" rel=\"nofollow\">\n          Reply\n         </a>\n        </div>\n       </article>\n       <!-- .comment-body -->\n      </li>\n      <?php } ?>\n      <?php if(showcomment(8296,10)){ ?>\n      <li class=\"comment even thread-even depth-1\" id=\"comment-1\">\n       <article class=\"comment-body\" id=\"div-comment-1\">\n        <footer class=\"comment-meta\">\n         <div class=\"comment-author vcard\">\n          <img alt=\"\" class=\"avatar avatar-32 photo\" height=\"32\" src=\"https://1.gravatar.com/avatar/1cb1c39857f5eef49897f849251861a9?s=32&amp;d=mm&amp;r=g\" srcset=\"https://1.gravatar.com/avatar/1cb1c39857f5eef49897f849251861a9?s=64&amp;d=mm&amp;r=g 2x\" width=\"32\"/>\n          <b class=\"fn\">\n           Dotilar\n          </b>\n          <span class=\"says\">\n           :\n          </span>\n         </div>\n         <!-- .comment-author -->\n         <div class=\"comment-metadata\">\n          <a href=\"http://dgquftlj2h3rhbalvz6o6s7ilg32bg763eqjyb76wlv4w2cndfzzrdid.onion/how/how-to-paint-laminate-furniture.html#comment-1\">\n           <time datetime=\"2020-10-18T03:55:58+00:00\">\n            18.10.2020 в 03:55\n           </time>\n          </a>\n         </div>\n        </footer>\n        <div class=\"comment-content\">\n         <p>\n          Completely I share your opinion. In it something is also to me your idea is pleasant. I suggest to take out for the general discussion.\n         </p>\n        </div>\n        <div class=\"reply\">\n         <a aria-label=\"Комментарий к записи Fenrit\" class=\"comment-reply-link\" data-belowelement=\"div-comment-1\" data-commentid=\"1\" data-postid=\"1\" data-respondelement=\"respond\" href=\"http://dgquftlj2h3rhbalvz6o6s7ilg32bg763eqjyb76wlv4w2cndfzzrdid.onion/how/how-to-paint-laminate-furniture.html?replytocom=1#respond\" rel=\"nofollow\">\n          Reply\n         </a>\n        </div>\n       </article>\n       <!-- .comment-body -->\n      </li>\n      <?php } ?>\n      <?php if(showcomment(8296,11)){ ?>\n      <li class=\"comment even thread-even depth-1\" id=\"comment-1\">\n       <article class=\"comment-body\" id=\"div-comment-1\">\n        <footer class=\"comment-meta\">\n         <div class=\"comment-author vcard\">\n          <img alt=\"\" class=\"avatar avatar-32 photo\" height=\"32\" src=\"https://1.gravatar.com/avatar/1cb1c39857f5eef49897f849251861a9?s=32&amp;d=mm&amp;r=g\" srcset=\"https://1.gravatar.com/avatar/1cb1c39857f5eef49897f849251861a9?s=64&amp;d=mm&amp;r=g 2x\" width=\"32\"/>\n          <b class=\"fn\">\n           Maunris\n          </b>\n          <span class=\"says\">\n           :\n          </span>\n         </div>\n         <!-- .comment-author -->\n         <div class=\"comment-metadata\">\n          <a href=\"http://dgquftlj2h3rhbalvz6o6s7ilg32bg763eqjyb76wlv4w2cndfzzrdid.onion/how/how-to-paint-laminate-furniture.html#comment-1\">\n           <time datetime=\"2020-10-18T05:00:20+00:00\">\n            18.10.2020 в 05:00\n           </time>\n          </a>\n         </div>\n        </footer>\n        <div class=\"comment-content\">\n         <p>\n          It is a pity, that now I can not express - it is very occupied. I will be released - I will necessarily express the opinion on this question.\n         </p>\n        </div>\n        <div class=\"reply\">\n         <a aria-label=\"Комментарий к записи Akinoran\" class=\"comment-reply-link\" data-belowelement=\"div-comment-1\" data-commentid=\"1\" data-postid=\"1\" data-respondelement=\"respond\" href=\"http://dgquftlj2h3rhbalvz6o6s7ilg32bg763eqjyb76wlv4w2cndfzzrdid.onion/how/how-to-paint-laminate-furniture.html?replytocom=1#respond\" rel=\"nofollow\">\n          Reply\n         </a>\n        </div>\n       </article>\n       <!-- .comment-body -->\n      </li>\n      <?php } ?>\n      <?php if(showcomment(8296,12)){ ?>\n      <li class=\"comment even thread-even depth-1\" id=\"comment-1\">\n       <article class=\"comment-body\" id=\"div-comment-1\">\n        <footer class=\"comment-meta\">\n         <div class=\"comment-author vcard\">\n          <img alt=\"\" class=\"avatar avatar-32 photo\" height=\"32\" src=\"https://1.gravatar.com/avatar/1cb1c39857f5eef49897f849251861a9?s=32&amp;d=mm&amp;r=g\" srcset=\"https://1.gravatar.com/avatar/1cb1c39857f5eef49897f849251861a9?s=64&amp;d=mm&amp;r=g 2x\" width=\"32\"/>\n          <b class=\"fn\">\n           Kajit\n          </b>\n          <span class=\"says\">\n           :\n          </span>\n         </div>\n         <!-- .comment-author -->\n         <div class=\"comment-metadata\">\n          <a href=\"http://dgquftlj2h3rhbalvz6o6s7ilg32bg763eqjyb76wlv4w2cndfzzrdid.onion/how/how-to-paint-laminate-furniture.html#comment-1\">\n           <time datetime=\"2020-10-18T05:39:04+00:00\">\n            18.10.2020 в 05:39\n           </time>\n          </a>\n         </div>\n        </footer>\n        <div class=\"comment-content\">\n         <p>\n          What necessary phrase... super, a brilliant idea\n         </p>\n        </div>\n        <div class=\"reply\">\n         <a aria-label=\"Комментарий к записи Narg\" class=\"comment-reply-link\" data-belowelement=\"div-comment-1\" data-commentid=\"1\" data-postid=\"1\" data-respondelement=\"respond\" href=\"http://dgquftlj2h3rhbalvz6o6s7ilg32bg763eqjyb76wlv4w2cndfzzrdid.onion/how/how-to-paint-laminate-furniture.html?replytocom=1#respond\" rel=\"nofollow\">\n          Reply\n         </a>\n        </div>\n       </article>\n       <!-- .comment-body -->\n      </li>\n      <?php } ?>\n      <?php if(showcomment(8296,13)){ ?>\n      <li class=\"comment even thread-even depth-1\" id=\"comment-1\">\n       <article class=\"comment-body\" id=\"div-comment-1\">\n        <footer class=\"comment-meta\">\n         <div class=\"comment-author vcard\">\n          <img alt=\"\" class=\"avatar avatar-32 photo\" height=\"32\" src=\"https://1.gravatar.com/avatar/1cb1c39857f5eef49897f849251861a9?s=32&amp;d=mm&amp;r=g\" srcset=\"https://1.gravatar.com/avatar/1cb1c39857f5eef49897f849251861a9?s=64&amp;d=mm&amp;r=g 2x\" width=\"32\"/>\n          <b class=\"fn\">\n           Metaxe\n          </b>\n          <span class=\"says\">\n           :\n          </span>\n         </div>\n         <!-- .comment-author -->\n         <div class=\"comment-metadata\">\n          <a href=\"http://dgquftlj2h3rhbalvz6o6s7ilg32bg763eqjyb76wlv4w2cndfzzrdid.onion/how/how-to-paint-laminate-furniture.html#comment-1\">\n           <time datetime=\"2020-10-18T09:13:10+00:00\">\n            18.10.2020 в 09:13\n           </time>\n          </a>\n         </div>\n        </footer>\n        <div class=\"comment-content\">\n         <p>\n          Your opinion, this your opinion\n         </p>\n        </div>\n        <div class=\"reply\">\n         <a aria-label=\"Комментарий к записи Nakree\" class=\"comment-reply-link\" data-belowelement=\"div-comment-1\" data-commentid=\"1\" data-postid=\"1\" data-respondelement=\"respond\" href=\"http://dgquftlj2h3rhbalvz6o6s7ilg32bg763eqjyb76wlv4w2cndfzzrdid.onion/how/how-to-paint-laminate-furniture.html?replytocom=1#respond\" rel=\"nofollow\">\n          Reply\n         </a>\n        </div>\n       </article>\n       <!-- .comment-body -->\n      </li>\n      <?php } ?>\n      <?php if(showcomment(8296,14)){ ?>\n      <li class=\"comment even thread-even depth-1\" id=\"comment-1\">\n       <article class=\"comment-body\" id=\"div-comment-1\">\n        <footer class=\"comment-meta\">\n         <div class=\"comment-author vcard\">\n          <img alt=\"\" class=\"avatar avatar-32 photo\" height=\"32\" src=\"https://1.gravatar.com/avatar/1cb1c39857f5eef49897f849251861a9?s=32&amp;d=mm&amp;r=g\" srcset=\"https://1.gravatar.com/avatar/1cb1c39857f5eef49897f849251861a9?s=64&amp;d=mm&amp;r=g 2x\" width=\"32\"/>\n          <b class=\"fn\">\n           Voodoojar\n          </b>\n          <span class=\"says\">\n           :\n          </span>\n         </div>\n         <!-- .comment-author -->\n         <div class=\"comment-metadata\">\n          <a href=\"http://dgquftlj2h3rhbalvz6o6s7ilg32bg763eqjyb76wlv4w2cndfzzrdid.onion/how/how-to-paint-laminate-furniture.html#comment-1\">\n           <time datetime=\"2020-10-18T11:43:24+00:00\">\n            18.10.2020 в 11:43\n           </time>\n          </a>\n         </div>\n        </footer>\n        <div class=\"comment-content\">\n         <p>\n          I think, that you commit an error. I can prove it. Write to me in PM, we will communicate.\n         </p>\n        </div>\n        <div class=\"reply\">\n         <a aria-label=\"Комментарий к записи Guzilkree\" class=\"comment-reply-link\" data-belowelement=\"div-comment-1\" data-commentid=\"1\" data-postid=\"1\" data-respondelement=\"respond\" href=\"http://dgquftlj2h3rhbalvz6o6s7ilg32bg763eqjyb76wlv4w2cndfzzrdid.onion/how/how-to-paint-laminate-furniture.html?replytocom=1#respond\" rel=\"nofollow\">\n          Reply\n         </a>\n        </div>\n       </article>\n       <!-- .comment-body -->\n      </li>\n      <?php } ?>\n      <?php if(showcomment(8296,15)){ ?>\n      <li class=\"comment even thread-even depth-1\" id=\"comment-1\">\n       <article class=\"comment-body\" id=\"div-comment-1\">\n        <footer class=\"comment-meta\">\n         <div class=\"comment-author vcard\">\n          <img alt=\"\" class=\"avatar avatar-32 photo\" height=\"32\" src=\"https://1.gravatar.com/avatar/1cb1c39857f5eef49897f849251861a9?s=32&amp;d=mm&amp;r=g\" srcset=\"https://1.gravatar.com/avatar/1cb1c39857f5eef49897f849251861a9?s=64&amp;d=mm&amp;r=g 2x\" width=\"32\"/>\n          <b class=\"fn\">\n           Maukus\n          </b>\n          <span class=\"says\">\n           :\n          </span>\n         </div>\n         <!-- .comment-author -->\n         <div class=\"comment-metadata\">\n          <a href=\"http://dgquftlj2h3rhbalvz6o6s7ilg32bg763eqjyb76wlv4w2cndfzzrdid.onion/how/how-to-paint-laminate-furniture.html#comment-1\">\n           <time datetime=\"2020-10-19T10:29:43+00:00\">\n            19.10.2020 в 10:29\n           </time>\n          </a>\n         </div>\n        </footer>\n        <div class=\"comment-content\">\n         <p>\n          The matchless message ;)\n         </p>\n        </div>\n        <div class=\"reply\">\n         <a aria-label=\"Комментарий к записи Malarr\" class=\"comment-reply-link\" data-belowelement=\"div-comment-1\" data-commentid=\"1\" data-postid=\"1\" data-respondelement=\"respond\" href=\"http://dgquftlj2h3rhbalvz6o6s7ilg32bg763eqjyb76wlv4w2cndfzzrdid.onion/how/how-to-paint-laminate-furniture.html?replytocom=1#respond\" rel=\"nofollow\">\n          Reply\n         </a>\n        </div>\n       </article>\n       <!-- .comment-body -->\n      </li>\n      <?php } ?>\n      <?php if(showcomment(8296,16)){ ?>\n      <li class=\"comment even thread-even depth-1\" id=\"comment-1\">\n       <article class=\"comment-body\" id=\"div-comment-1\">\n        <footer class=\"comment-meta\">\n         <div class=\"comment-author vcard\">\n          <img alt=\"\" class=\"avatar avatar-32 photo\" height=\"32\" src=\"https://1.gravatar.com/avatar/1cb1c39857f5eef49897f849251861a9?s=32&amp;d=mm&amp;r=g\" srcset=\"https://1.gravatar.com/avatar/1cb1c39857f5eef49897f849251861a9?s=64&amp;d=mm&amp;r=g 2x\" width=\"32\"/>\n          <b class=\"fn\">\n           Kakus\n          </b>\n          <span class=\"says\">\n           :\n          </span>\n         </div>\n         <!-- .comment-author -->\n         <div class=\"comment-metadata\">\n          <a href=\"http://dgquftlj2h3rhbalvz6o6s7ilg32bg763eqjyb76wlv4w2cndfzzrdid.onion/how/how-to-paint-laminate-furniture.html#comment-1\">\n           <time datetime=\"2020-10-19T16:35:06+00:00\">\n            19.10.2020 в 16:35\n           </time>\n          </a>\n         </div>\n        </footer>\n        <div class=\"comment-content\">\n         <p>\n          I apologise, but, in my opinion, you are mistaken. Write to me in PM.\n         </p>\n        </div>\n        <div class=\"reply\">\n         <a aria-label=\"Комментарий к записи Vura\" class=\"comment-reply-link\" data-belowelement=\"div-comment-1\" data-commentid=\"1\" data-postid=\"1\" data-respondelement=\"respond\" href=\"http://dgquftlj2h3rhbalvz6o6s7ilg32bg763eqjyb76wlv4w2cndfzzrdid.onion/how/how-to-paint-laminate-furniture.html?replytocom=1#respond\" rel=\"nofollow\">\n          Reply\n         </a>\n        </div>\n       </article>\n       <!-- .comment-body -->\n      </li>\n      <?php } ?>\n      <?php if(showcomment(8296,17)){ ?>\n      <li class=\"comment even thread-even depth-1\" id=\"comment-1\">\n       <article class=\"comment-body\" id=\"div-comment-1\">\n        <footer class=\"comment-meta\">\n         <div class=\"comment-author vcard\">\n          <img alt=\"\" class=\"avatar avatar-32 photo\" height=\"32\" src=\"https://1.gravatar.com/avatar/1cb1c39857f5eef49897f849251861a9?s=32&amp;d=mm&amp;r=g\" srcset=\"https://1.gravatar.com/avatar/1cb1c39857f5eef49897f849251861a9?s=64&amp;d=mm&amp;r=g 2x\" width=\"32\"/>\n          <b class=\"fn\">\n           Malarisar\n          </b>\n          <span class=\"says\">\n           :\n          </span>\n         </div>\n         <!-- .comment-author -->\n         <div class=\"comment-metadata\">\n          <a href=\"http://dgquftlj2h3rhbalvz6o6s7ilg32bg763eqjyb76wlv4w2cndfzzrdid.onion/how/how-to-paint-laminate-furniture.html#comment-1\">\n           <time datetime=\"2020-10-20T10:39:31+00:00\">\n            20.10.2020 в 10:39\n           </time>\n          </a>\n         </div>\n        </footer>\n        <div class=\"comment-content\">\n         <p>\n          The exact answer\n         </p>\n        </div>\n        <div class=\"reply\">\n         <a aria-label=\"Комментарий к записи Dougul\" class=\"comment-reply-link\" data-belowelement=\"div-comment-1\" data-commentid=\"1\" data-postid=\"1\" data-respondelement=\"respond\" href=\"http://dgquftlj2h3rhbalvz6o6s7ilg32bg763eqjyb76wlv4w2cndfzzrdid.onion/how/how-to-paint-laminate-furniture.html?replytocom=1#respond\" rel=\"nofollow\">\n          Reply\n         </a>\n        </div>\n       </article>\n       <!-- .comment-body -->\n      </li>\n      <?php } ?>\n      <?php if(showcomment(8296,18)){ ?>\n      <li class=\"comment even thread-even depth-1\" id=\"comment-1\">\n       <article class=\"comment-body\" id=\"div-comment-1\">\n        <footer class=\"comment-meta\">\n         <div class=\"comment-author vcard\">\n          <img alt=\"\" class=\"avatar avatar-32 photo\" height=\"32\" src=\"https://1.gravatar.com/avatar/1cb1c39857f5eef49897f849251861a9?s=32&amp;d=mm&amp;r=g\" srcset=\"https://1.gravatar.com/avatar/1cb1c39857f5eef49897f849251861a9?s=64&amp;d=mm&amp;r=g 2x\" width=\"32\"/>\n          <b class=\"fn\">\n           Taumuro\n          </b>\n          <span class=\"says\">\n           :\n          </span>\n         </div>\n         <!-- .comment-author -->\n         <div class=\"comment-metadata\">\n          <a href=\"http://dgquftlj2h3rhbalvz6o6s7ilg32bg763eqjyb76wlv4w2cndfzzrdid.onion/how/how-to-paint-laminate-furniture.html#comment-1\">\n           <time datetime=\"2020-10-20T17:08:01+00:00\">\n            20.10.2020 в 17:08\n           </time>\n          </a>\n         </div>\n        </footer>\n        <div class=\"comment-content\">\n         <p>\n          The nice answer\n         </p>\n        </div>\n        <div class=\"reply\">\n         <a aria-label=\"Комментарий к записи Dalrajas\" class=\"comment-reply-link\" data-belowelement=\"div-comment-1\" data-commentid=\"1\" data-postid=\"1\" data-respondelement=\"respond\" href=\"http://dgquftlj2h3rhbalvz6o6s7ilg32bg763eqjyb76wlv4w2cndfzzrdid.onion/how/how-to-paint-laminate-furniture.html?replytocom=1#respond\" rel=\"nofollow\">\n          Reply\n         </a>\n        </div>\n       </article>\n       <!-- .comment-body -->\n      </li>\n      <?php } ?>\n      <?php if(showcomment(8296,19)){ ?>\n      <li class=\"comment even thread-even depth-1\" id=\"comment-1\">\n       <article class=\"comment-body\" id=\"div-comment-1\">\n        <footer class=\"comment-meta\">\n         <div class=\"comment-author vcard\">\n          <img alt=\"\" class=\"avatar avatar-32 photo\" height=\"32\" src=\"https://1.gravatar.com/avatar/1cb1c39857f5eef49897f849251861a9?s=32&amp;d=mm&amp;r=g\" srcset=\"https://1.gravatar.com/avatar/1cb1c39857f5eef49897f849251861a9?s=64&amp;d=mm&amp;r=g 2x\" width=\"32\"/>\n          <b class=\"fn\">\n           Zulkijind\n          </b>\n          <span class=\"says\">\n           :\n          </span>\n         </div>\n         <!-- .comment-author -->\n         <div class=\"comment-metadata\">\n          <a href=\"http://dgquftlj2h3rhbalvz6o6s7ilg32bg763eqjyb76wlv4w2cndfzzrdid.onion/how/how-to-paint-laminate-furniture.html#comment-1\">\n           <time datetime=\"2020-10-20T21:53:37+00:00\">\n            20.10.2020 в 21:53\n           </time>\n          </a>\n         </div>\n        </footer>\n        <div class=\"comment-content\">\n         <p>\n          It is remarkable, this rather valuable message\n         </p>\n        </div>\n        <div class=\"reply\">\n         <a aria-label=\"Комментарий к записи Kazilabar\" class=\"comment-reply-link\" data-belowelement=\"div-comment-1\" data-commentid=\"1\" data-postid=\"1\" data-respondelement=\"respond\" href=\"http://dgquftlj2h3rhbalvz6o6s7ilg32bg763eqjyb76wlv4w2cndfzzrdid.onion/how/how-to-paint-laminate-furniture.html?replytocom=1#respond\" rel=\"nofollow\">\n          Reply\n         </a>\n        </div>\n       </article>\n       <!-- .comment-body -->\n      </li>\n      <?php } ?>\n      <?php if(showcomment(8296,20)){ ?>\n      <li class=\"comment even thread-even depth-1\" id=\"comment-1\">\n       <article class=\"comment-body\" id=\"div-comment-1\">\n        <footer class=\"comment-meta\">\n         <div class=\"comment-author vcard\">\n          <img alt=\"\" class=\"avatar avatar-32 photo\" height=\"32\" src=\"https://1.gravatar.com/avatar/1cb1c39857f5eef49897f849251861a9?s=32&amp;d=mm&amp;r=g\" srcset=\"https://1.gravatar.com/avatar/1cb1c39857f5eef49897f849251861a9?s=64&amp;d=mm&amp;r=g 2x\" width=\"32\"/>\n          <b class=\"fn\">\n           Mazukree\n          </b>\n          <span class=\"says\">\n           :\n          </span>\n         </div>\n         <!-- .comment-author -->\n         <div class=\"comment-metadata\">\n          <a href=\"http://dgquftlj2h3rhbalvz6o6s7ilg32bg763eqjyb76wlv4w2cndfzzrdid.onion/how/how-to-paint-laminate-furniture.html#comment-1\">\n           <time datetime=\"2020-10-22T00:55:06+00:00\">\n            22.10.2020 в 00:55\n           </time>\n          </a>\n         </div>\n        </footer>\n        <div class=\"comment-content\">\n         <p>\n          It is remarkable, rather valuable piece\n         </p>\n        </div>\n        <div class=\"reply\">\n         <a aria-label=\"Комментарий к записи Grozragore\" class=\"comment-reply-link\" data-belowelement=\"div-comment-1\" data-commentid=\"1\" data-postid=\"1\" data-respondelement=\"respond\" href=\"http://dgquftlj2h3rhbalvz6o6s7ilg32bg763eqjyb76wlv4w2cndfzzrdid.onion/how/how-to-paint-laminate-furniture.html?replytocom=1#respond\" rel=\"nofollow\">\n          Reply\n         </a>\n        </div>\n       </article>\n       <!-- .comment-body -->\n      </li>\n      <?php } ?>\n      <?php if(showcomment(8296,21)){ ?>\n      <li class=\"comment even thread-even depth-1\" id=\"comment-1\">\n       <article class=\"comment-body\" id=\"div-comment-1\">\n        <footer class=\"comment-meta\">\n         <div class=\"comment-author vcard\">\n          <img alt=\"\" class=\"avatar avatar-32 photo\" height=\"32\" src=\"https://1.gravatar.com/avatar/1cb1c39857f5eef49897f849251861a9?s=32&amp;d=mm&amp;r=g\" srcset=\"https://1.gravatar.com/avatar/1cb1c39857f5eef49897f849251861a9?s=64&amp;d=mm&amp;r=g 2x\" width=\"32\"/>\n          <b class=\"fn\">\n           Vozil\n          </b>\n          <span class=\"says\">\n           :\n          </span>\n         </div>\n         <!-- .comment-author -->\n         <div class=\"comment-metadata\">\n          <a href=\"http://dgquftlj2h3rhbalvz6o6s7ilg32bg763eqjyb76wlv4w2cndfzzrdid.onion/how/how-to-paint-laminate-furniture.html#comment-1\">\n           <time datetime=\"2020-10-22T05:41:32+00:00\">\n            22.10.2020 в 05:41\n           </time>\n          </a>\n         </div>\n        </footer>\n        <div class=\"comment-content\">\n         <p>\n          It is not logical\n         </p>\n        </div>\n        <div class=\"reply\">\n         <a aria-label=\"Комментарий к записи Akinotaxe\" class=\"comment-reply-link\" data-belowelement=\"div-comment-1\" data-commentid=\"1\" data-postid=\"1\" data-respondelement=\"respond\" href=\"http://dgquftlj2h3rhbalvz6o6s7ilg32bg763eqjyb76wlv4w2cndfzzrdid.onion/how/how-to-paint-laminate-furniture.html?replytocom=1#respond\" rel=\"nofollow\">\n          Reply\n         </a>\n        </div>\n       </article>\n       <!-- .comment-body -->\n      </li>\n      <?php } ?>\n      <?php if(showcomment(8296,22)){ ?>\n      <li class=\"comment even thread-even depth-1\" id=\"comment-1\">\n       <article class=\"comment-body\" id=\"div-comment-1\">\n        <footer class=\"comment-meta\">\n         <div class=\"comment-author vcard\">\n          <img alt=\"\" class=\"avatar avatar-32 photo\" height=\"32\" src=\"https://1.gravatar.com/avatar/1cb1c39857f5eef49897f849251861a9?s=32&amp;d=mm&amp;r=g\" srcset=\"https://1.gravatar.com/avatar/1cb1c39857f5eef49897f849251861a9?s=64&amp;d=mm&amp;r=g 2x\" width=\"32\"/>\n          <b class=\"fn\">\n           Arashakar\n          </b>\n          <span class=\"says\">\n           :\n          </span>\n         </div>\n         <!-- .comment-author -->\n         <div class=\"comment-metadata\">\n          <a href=\"http://dgquftlj2h3rhbalvz6o6s7ilg32bg763eqjyb76wlv4w2cndfzzrdid.onion/how/how-to-paint-laminate-furniture.html#comment-1\">\n           <time datetime=\"2020-10-22T09:24:14+00:00\">\n            22.10.2020 в 09:24\n           </time>\n          </a>\n         </div>\n        </footer>\n        <div class=\"comment-content\">\n         <p>\n          I think, that you are mistaken. Write to me in PM, we will talk.\n         </p>\n        </div>\n        <div class=\"reply\">\n         <a aria-label=\"Комментарий к записи Meziramar\" class=\"comment-reply-link\" data-belowelement=\"div-comment-1\" data-commentid=\"1\" data-postid=\"1\" data-respondelement=\"respond\" href=\"http://dgquftlj2h3rhbalvz6o6s7ilg32bg763eqjyb76wlv4w2cndfzzrdid.onion/how/how-to-paint-laminate-furniture.html?replytocom=1#respond\" rel=\"nofollow\">\n          Reply\n         </a>\n        </div>\n       </article>\n       <!-- .comment-body -->\n      </li>\n      <?php } ?>\n      <?php if(showcomment(8296,23)){ ?>\n      <li class=\"comment even thread-even depth-1\" id=\"comment-1\">\n       <article class=\"comment-body\" id=\"div-comment-1\">\n        <footer class=\"comment-meta\">\n         <div class=\"comment-author vcard\">\n          <img alt=\"\" class=\"avatar avatar-32 photo\" height=\"32\" src=\"https://1.gravatar.com/avatar/1cb1c39857f5eef49897f849251861a9?s=32&amp;d=mm&amp;r=g\" srcset=\"https://1.gravatar.com/avatar/1cb1c39857f5eef49897f849251861a9?s=64&amp;d=mm&amp;r=g 2x\" width=\"32\"/>\n          <b class=\"fn\">\n           Dim\n          </b>\n          <span class=\"says\">\n           :\n          </span>\n         </div>\n         <!-- .comment-author -->\n         <div class=\"comment-metadata\">\n          <a href=\"http://dgquftlj2h3rhbalvz6o6s7ilg32bg763eqjyb76wlv4w2cndfzzrdid.onion/how/how-to-paint-laminate-furniture.html#comment-1\">\n           <time datetime=\"2020-10-22T23:31:48+00:00\">\n            22.10.2020 в 23:31\n           </time>\n          </a>\n         </div>\n        </footer>\n        <div class=\"comment-content\">\n         <p>\n          I congratulate, what words..., an excellent idea\n         </p>\n        </div>\n        <div class=\"reply\">\n         <a aria-label=\"Комментарий к записи Nikogul\" class=\"comment-reply-link\" data-belowelement=\"div-comment-1\" data-commentid=\"1\" data-postid=\"1\" data-respondelement=\"respond\" href=\"http://dgquftlj2h3rhbalvz6o6s7ilg32bg763eqjyb76wlv4w2cndfzzrdid.onion/how/how-to-paint-laminate-furniture.html?replytocom=1#respond\" rel=\"nofollow\">\n          Reply\n         </a>\n        </div>\n       </article>\n       <!-- .comment-body -->\n      </li>\n      <?php } ?>\n      <?php if(showcomment(8296,24)){ ?>\n      <li class=\"comment even thread-even depth-1\" id=\"comment-1\">\n       <article class=\"comment-body\" id=\"div-comment-1\">\n        <footer class=\"comment-meta\">\n         <div class=\"comment-author vcard\">\n          <img alt=\"\" class=\"avatar avatar-32 photo\" height=\"32\" src=\"https://1.gravatar.com/avatar/1cb1c39857f5eef49897f849251861a9?s=32&amp;d=mm&amp;r=g\" srcset=\"https://1.gravatar.com/avatar/1cb1c39857f5eef49897f849251861a9?s=64&amp;d=mm&amp;r=g 2x\" width=\"32\"/>\n          <b class=\"fn\">\n           Mikalkree\n          </b>\n          <span class=\"says\">\n           :\n          </span>\n         </div>\n         <!-- .comment-author -->\n         <div class=\"comment-metadata\">\n          <a href=\"http://dgquftlj2h3rhbalvz6o6s7ilg32bg763eqjyb76wlv4w2cndfzzrdid.onion/how/how-to-paint-laminate-furniture.html#comment-1\">\n           <time datetime=\"2020-10-23T00:24:46+00:00\">\n            23.10.2020 в 00:24\n           </time>\n          </a>\n         </div>\n        </footer>\n        <div class=\"comment-content\">\n         <p>\n          Why also is not present?\n         </p>\n        </div>\n        <div class=\"reply\">\n         <a aria-label=\"Комментарий к записи Megore\" class=\"comment-reply-link\" data-belowelement=\"div-comment-1\" data-commentid=\"1\" data-postid=\"1\" data-respondelement=\"respond\" href=\"http://dgquftlj2h3rhbalvz6o6s7ilg32bg763eqjyb76wlv4w2cndfzzrdid.onion/how/how-to-paint-laminate-furniture.html?replytocom=1#respond\" rel=\"nofollow\">\n          Reply\n         </a>\n        </div>\n       </article>\n       <!-- .comment-body -->\n      </li>\n      <?php } ?>\n      <?php if(showcomment(8296,25)){ ?>\n      <li class=\"comment even thread-even depth-1\" id=\"comment-1\">\n       <article class=\"comment-body\" id=\"div-comment-1\">\n        <footer class=\"comment-meta\">\n         <div class=\"comment-author vcard\">\n          <img alt=\"\" class=\"avatar avatar-32 photo\" height=\"32\" src=\"https://1.gravatar.com/avatar/1cb1c39857f5eef49897f849251861a9?s=32&amp;d=mm&amp;r=g\" srcset=\"https://1.gravatar.com/avatar/1cb1c39857f5eef49897f849251861a9?s=64&amp;d=mm&amp;r=g 2x\" width=\"32\"/>\n          <b class=\"fn\">\n           Kiganris\n          </b>\n          <span class=\"says\">\n           :\n          </span>\n         </div>\n         <!-- .comment-author -->\n         <div class=\"comment-metadata\">\n          <a href=\"http://dgquftlj2h3rhbalvz6o6s7ilg32bg763eqjyb76wlv4w2cndfzzrdid.onion/how/how-to-paint-laminate-furniture.html#comment-1\">\n           <time datetime=\"2020-10-23T06:38:51+00:00\">\n            23.10.2020 в 06:38\n           </time>\n          </a>\n         </div>\n        </footer>\n        <div class=\"comment-content\">\n         <p>\n          You are not right. Let's discuss. Write to me in PM, we will talk.\n         </p>\n        </div>\n        <div class=\"reply\">\n         <a aria-label=\"Комментарий к записи Tetaur\" class=\"comment-reply-link\" data-belowelement=\"div-comment-1\" data-commentid=\"1\" data-postid=\"1\" data-respondelement=\"respond\" href=\"http://dgquftlj2h3rhbalvz6o6s7ilg32bg763eqjyb76wlv4w2cndfzzrdid.onion/how/how-to-paint-laminate-furniture.html?replytocom=1#respond\" rel=\"nofollow\">\n          Reply\n         </a>\n        </div>\n       </article>\n       <!-- .comment-body -->\n      </li>\n      <?php } ?>\n     </ul>\n     <hr/>\n     <div class=\"comment-respond\" id=\"respond\">\n      <h3 class=\"comment-reply-title\" id=\"reply-title\">\n       Добавить комментарий\n       <small>\n        <a href=\"http://dgquftlj2h3rhbalvz6o6s7ilg32bg763eqjyb76wlv4w2cndfzzrdid.onion/how/how-to-paint-laminate-furniture.html#respond\" id=\"cancel-comment-reply-link\" rel=\"nofollow\" style=\"display:none;\">\n         Отменить ответ\n        </a>\n       </small>\n      </h3>\n      <form action=\"http://dgquftlj2h3rhbalvz6o6s7ilg32bg763eqjyb76wlv4w2cndfzzrdid.onion\" class=\"comment-form\" id=\"commentform\" method=\"post\" novalidate=\"\">\n       <p class=\"comment-notes\">\n        <span id=\"email-notes\">\n         Ваш e-mail не будет опубликован.\n        </span>\n        Обязательные поля помечены\n        <span class=\"required\">\n         *\n        </span>\n       </p>\n       <p class=\"comment-form-comment\">\n        <label for=\"comment\">\n         Комментарий\n        </label>\n        <textarea cols=\"45\" id=\"comment\" maxlength=\"65525\" name=\"comment\" required=\"required\" rows=\"8\"></textarea>\n       </p>\n       <p class=\"comment-form-author\">\n        <label for=\"author\">\n         Имя\n         <span class=\"required\">\n          *\n         </span>\n        </label>\n        <input id=\"author\" maxlength=\"245\" name=\"author\" required=\"required\" size=\"30\" type=\"text\" value=\"\"/>\n       </p>\n       <p class=\"comment-form-email\">\n        <label for=\"email\">\n         E-mail\n         <span class=\"required\">\n          *\n         </span>\n        </label>\n        <input aria-describedby=\"email-notes\" id=\"email\" maxlength=\"100\" name=\"email\" required=\"required\" size=\"30\" type=\"email\" value=\"\"/>\n       </p>\n       <p class=\"comment-form-cookies-consent\">\n        <input id=\"wp-comment-cookies-consent\" name=\"wp-comment-cookies-consent\" type=\"checkbox\" value=\"yes\"/>\n        <label for=\"wp-comment-cookies-consent\">\n         Сохранить моё имя, email и адрес сайта в этом браузере для последующих моих комментариев.\n        </label>\n       </p>\n       <p class=\"form-submit\">\n        <input class=\"submit\" id=\"submit\" name=\"submit\" type=\"submit\" value=\"Отправить комментарий\"/>\n        <input id=\"comment_post_ID\" name=\"comment_post_ID\" type=\"hidden\" value=\"1\"/>\n        <input id=\"comment_parent\" name=\"comment_parent\" type=\"hidden\" value=\"0\"/>\n       </p>\n      </form>\n     </div>\n    </article>\n   </section>\n   <div class=\"site-content-pagination\">\n    <nav aria-label=\"Записи\" class=\"navigation pagination\" role=\"navigation\">\n     <h2 class=\"screen-reader-text\">\n      Навигация по записям\n     </h2>\n     <div class=\"nav-links\">\n      <span aria-current=\"page\" class=\"page-numbers current\">\n       1\n      </span>\n      <a class=\"page-numbers\" href=\"http://dgquftlj2h3rhbalvz6o6s7ilg32bg763eqjyb76wlv4w2cndfzzrdid.onion/app/hacker-kid-app.html\">\n       2\n      </a>\n      <a class=\"next page-numbers\" href=\"http://dgquftlj2h3rhbalvz6o6s7ilg32bg763eqjyb76wlv4w2cndfzzrdid.onion/hacker/what-does-mark-zuckerberg-own.html\">\n       Далее\n      </a>\n     </div>\n    </nav>\n   </div>\n  </main>\n  <hr/>\n  <footer>\n   <div id=\"footer-menu-wrapper\">\n    <nav id=\"footer-menu\">\n    </nav>\n   </div>\n   <div id=\"footer-widget-wrapper\">\n    <div id=\"footer-widget-wrapper-left\">\n     <div class=\"widget widget_search\" id=\"search-2\">\n      <form action=\"http://dgquftlj2h3rhbalvz6o6s7ilg32bg763eqjyb76wlv4w2cndfzzrdid.onion/\" class=\"search-form\" method=\"get\" role=\"search\">\n       <input class=\"search-submit\" type=\"submit\" value=\"Поиск\"/>\n      </form>\n     </div>\n     <div class=\"widget widget_archive\" id=\"archives-2\">\n      <h3 class=\"widget-title\">\n       Архивы\n      </h3>\n      <ul>\n       <li>\n        <a href=\"http://dgquftlj2h3rhbalvz6o6s7ilg32bg763eqjyb76wlv4w2cndfzzrdid.onion/hack-2020/chromecast-hacks-2020.html\">\n         2019\n        </a>\n       </li>\n       <li>\n        <a href=\"http://dgquftlj2h3rhbalvz6o6s7ilg32bg763eqjyb76wlv4w2cndfzzrdid.onion/2020/gta-v-injector-2020.html\">\n         2018\n        </a>\n       </li>\n      </ul>\n     </div>\n     <div class=\"widget widget_categories\" id=\"categories-2\">\n      <h3 class=\"widget-title\">\n       Рубрики\n      </h3>\n      <ul>\n       <li class=\"cat-item cat-item-17\">\n        <a href=\"http://dgquftlj2h3rhbalvz6o6s7ilg32bg763eqjyb76wlv4w2cndfzzrdid.onion/2020/\">\n         2020\n        </a>\n       </li>\n       <li class=\"cat-item cat-item-17\">\n        <a href=\"http://dgquftlj2h3rhbalvz6o6s7ilg32bg763eqjyb76wlv4w2cndfzzrdid.onion/account/\">\n         Account\n        </a>\n       </li>\n       <li class=\"cat-item cat-item-17\">\n        <a href=\"http://dgquftlj2h3rhbalvz6o6s7ilg32bg763eqjyb76wlv4w2cndfzzrdid.onion/and/\">\n         And\n        </a>\n       </li>\n       <li class=\"cat-item cat-item-17\">\n        <a href=\"http://dgquftlj2h3rhbalvz6o6s7ilg32bg763eqjyb76wlv4w2cndfzzrdid.onion/android/\">\n         Android\n        </a>\n       </li>\n       <li class=\"cat-item cat-item-17\">\n        <a href=\"http://dgquftlj2h3rhbalvz6o6s7ilg32bg763eqjyb76wlv4w2cndfzzrdid.onion/apk/\">\n         Apk\n        </a>\n       </li>\n       <li class=\"cat-item cat-item-17\">\n        <a href=\"http://dgquftlj2h3rhbalvz6o6s7ilg32bg763eqjyb76wlv4w2cndfzzrdid.onion/app/\">\n         App\n        </a>\n       </li>\n       <li class=\"cat-item cat-item-17\">\n        <a href=\"http://dgquftlj2h3rhbalvz6o6s7ilg32bg763eqjyb76wlv4w2cndfzzrdid.onion/attack/\">\n         Attack\n        </a>\n       </li>\n       <li class=\"cat-item cat-item-17\">\n        <a href=\"http://dgquftlj2h3rhbalvz6o6s7ilg32bg763eqjyb76wlv4w2cndfzzrdid.onion/best/\">\n         Best\n        </a>\n       </li>\n       <li class=\"cat-item cat-item-17\">\n        <a href=\"http://dgquftlj2h3rhbalvz6o6s7ilg32bg763eqjyb76wlv4w2cndfzzrdid.onion/card/\">\n         Card\n        </a>\n       </li>\n       <li class=\"cat-item cat-item-17\">\n        <a href=\"http://dgquftlj2h3rhbalvz6o6s7ilg32bg763eqjyb76wlv4w2cndfzzrdid.onion/cheats/\">\n         Cheats\n        </a>\n       </li>\n       <li class=\"cat-item cat-item-17\">\n        <a href=\"http://dgquftlj2h3rhbalvz6o6s7ilg32bg763eqjyb76wlv4w2cndfzzrdid.onion/codes/\">\n         Codes\n        </a>\n       </li>\n       <li class=\"cat-item cat-item-17\">\n        <a href=\"http://dgquftlj2h3rhbalvz6o6s7ilg32bg763eqjyb76wlv4w2cndfzzrdid.onion/download/\">\n         Download\n        </a>\n       </li>\n       <li class=\"cat-item cat-item-17\">\n        <a href=\"http://dgquftlj2h3rhbalvz6o6s7ilg32bg763eqjyb76wlv4w2cndfzzrdid.onion/email/\">\n         Email\n        </a>\n       </li>\n       <li class=\"cat-item cat-item-17\">\n        <a href=\"http://dgquftlj2h3rhbalvz6o6s7ilg32bg763eqjyb76wlv4w2cndfzzrdid.onion/engine/\">\n         Engine\n        </a>\n       </li>\n       <li class=\"cat-item cat-item-17\">\n        <a href=\"http://dgquftlj2h3rhbalvz6o6s7ilg32bg763eqjyb76wlv4w2cndfzzrdid.onion/ethical/\">\n         Ethical\n        </a>\n       </li>\n       <li class=\"cat-item cat-item-17\">\n        <a href=\"http://dgquftlj2h3rhbalvz6o6s7ilg32bg763eqjyb76wlv4w2cndfzzrdid.onion/facebook/\">\n         Facebook\n        </a>\n       </li>\n       <li class=\"cat-item cat-item-17\">\n        <a href=\"http://dgquftlj2h3rhbalvz6o6s7ilg32bg763eqjyb76wlv4w2cndfzzrdid.onion/for/\">\n         For\n        </a>\n       </li>\n       <li class=\"cat-item cat-item-17\">\n        <a href=\"http://dgquftlj2h3rhbalvz6o6s7ilg32bg763eqjyb76wlv4w2cndfzzrdid.onion/free/\">\n         Free\n        </a>\n       </li>\n       <li class=\"cat-item cat-item-17\">\n        <a href=\"http://dgquftlj2h3rhbalvz6o6s7ilg32bg763eqjyb76wlv4w2cndfzzrdid.onion/game/\">\n         Game\n        </a>\n       </li>\n       <li class=\"cat-item cat-item-17\">\n        <a href=\"http://dgquftlj2h3rhbalvz6o6s7ilg32bg763eqjyb76wlv4w2cndfzzrdid.onion/get/\">\n         Get\n        </a>\n       </li>\n       <li class=\"cat-item cat-item-17\">\n        <a href=\"http://dgquftlj2h3rhbalvz6o6s7ilg32bg763eqjyb76wlv4w2cndfzzrdid.onion/hack/\">\n         Hack\n        </a>\n       </li>\n       <li class=\"cat-item cat-item-17\">\n        <a href=\"http://dgquftlj2h3rhbalvz6o6s7ilg32bg763eqjyb76wlv4w2cndfzzrdid.onion/hack-2020/\">\n         Hack 2020\n        </a>\n       </li>\n       <li class=\"cat-item cat-item-17\">\n        <a href=\"http://dgquftlj2h3rhbalvz6o6s7ilg32bg763eqjyb76wlv4w2cndfzzrdid.onion/hacker/\">\n         Hacker\n        </a>\n       </li>\n       <li class=\"cat-item cat-item-17\">\n        <a href=\"http://dgquftlj2h3rhbalvz6o6s7ilg32bg763eqjyb76wlv4w2cndfzzrdid.onion/how/\">\n         How\n        </a>\n       </li>\n       <li class=\"cat-item cat-item-17\">\n        <a href=\"http://dgquftlj2h3rhbalvz6o6s7ilg32bg763eqjyb76wlv4w2cndfzzrdid.onion/how-hack/\">\n         How hack\n        </a>\n       </li>\n       <li class=\"cat-item cat-item-17\">\n        <a href=\"http://dgquftlj2h3rhbalvz6o6s7ilg32bg763eqjyb76wlv4w2cndfzzrdid.onion/ikea/\">\n         Ikea\n        </a>\n       </li>\n       <li class=\"cat-item cat-item-17\">\n        <a href=\"http://dgquftlj2h3rhbalvz6o6s7ilg32bg763eqjyb76wlv4w2cndfzzrdid.onion/ikea-hack/\">\n         Ikea hack\n        </a>\n       </li>\n       <li class=\"cat-item cat-item-17\">\n        <a href=\"http://dgquftlj2h3rhbalvz6o6s7ilg32bg763eqjyb76wlv4w2cndfzzrdid.onion/ios/\">\n         Ios\n        </a>\n       </li>\n       <li class=\"cat-item cat-item-17\">\n        <a href=\"http://dgquftlj2h3rhbalvz6o6s7ilg32bg763eqjyb76wlv4w2cndfzzrdid.onion/kali/\">\n         Kali\n        </a>\n       </li>\n       <li class=\"cat-item cat-item-17\">\n        <a href=\"http://dgquftlj2h3rhbalvz6o6s7ilg32bg763eqjyb76wlv4w2cndfzzrdid.onion/mario/\">\n         Mario\n        </a>\n       </li>\n       <li class=\"cat-item cat-item-17\">\n        <a href=\"http://dgquftlj2h3rhbalvz6o6s7ilg32bg763eqjyb76wlv4w2cndfzzrdid.onion/minecraft/\">\n         Minecraft\n        </a>\n       </li>\n       <li class=\"cat-item cat-item-17\">\n        <a href=\"http://dgquftlj2h3rhbalvz6o6s7ilg32bg763eqjyb76wlv4w2cndfzzrdid.onion/mobile/\">\n         Mobile\n        </a>\n       </li>\n       <li class=\"cat-item cat-item-17\">\n        <a href=\"http://dgquftlj2h3rhbalvz6o6s7ilg32bg763eqjyb76wlv4w2cndfzzrdid.onion/mod-apk/\">\n         Mod apk\n        </a>\n       </li>\n       <li class=\"cat-item cat-item-17\">\n        <a href=\"http://dgquftlj2h3rhbalvz6o6s7ilg32bg763eqjyb76wlv4w2cndfzzrdid.onion/money/\">\n         Money\n        </a>\n       </li>\n       <li class=\"cat-item cat-item-17\">\n        <a href=\"http://dgquftlj2h3rhbalvz6o6s7ilg32bg763eqjyb76wlv4w2cndfzzrdid.onion/online/\">\n         Online\n        </a>\n       </li>\n       <li class=\"cat-item cat-item-17\">\n        <a href=\"http://dgquftlj2h3rhbalvz6o6s7ilg32bg763eqjyb76wlv4w2cndfzzrdid.onion/password/\">\n         Password\n        </a>\n       </li>\n       <li class=\"cat-item cat-item-17\">\n        <a href=\"http://dgquftlj2h3rhbalvz6o6s7ilg32bg763eqjyb76wlv4w2cndfzzrdid.onion/pdf/\">\n         Pdf\n        </a>\n       </li>\n       <li class=\"cat-item cat-item-17\">\n        <a href=\"http://dgquftlj2h3rhbalvz6o6s7ilg32bg763eqjyb76wlv4w2cndfzzrdid.onion/pokemon/\">\n         Pokemon\n        </a>\n       </li>\n       <li class=\"cat-item cat-item-17\">\n        <a href=\"http://dgquftlj2h3rhbalvz6o6s7ilg32bg763eqjyb76wlv4w2cndfzzrdid.onion/pubg/\">\n         Pubg\n        </a>\n       </li>\n       <li class=\"cat-item cat-item-17\">\n        <a href=\"http://dgquftlj2h3rhbalvz6o6s7ilg32bg763eqjyb76wlv4w2cndfzzrdid.onion/reddit/\">\n         Reddit\n        </a>\n       </li>\n       <li class=\"cat-item cat-item-17\">\n        <a href=\"http://dgquftlj2h3rhbalvz6o6s7ilg32bg763eqjyb76wlv4w2cndfzzrdid.onion/rom/\">\n         Rom\n        </a>\n       </li>\n       <li class=\"cat-item cat-item-17\">\n        <a href=\"http://dgquftlj2h3rhbalvz6o6s7ilg32bg763eqjyb76wlv4w2cndfzzrdid.onion/security/\">\n         Security\n        </a>\n       </li>\n       <li class=\"cat-item cat-item-17\">\n        <a href=\"http://dgquftlj2h3rhbalvz6o6s7ilg32bg763eqjyb76wlv4w2cndfzzrdid.onion/sonic/\">\n         Sonic\n        </a>\n       </li>\n       <li class=\"cat-item cat-item-17\">\n        <a href=\"http://dgquftlj2h3rhbalvz6o6s7ilg32bg763eqjyb76wlv4w2cndfzzrdid.onion/table/\">\n         Table\n        </a>\n       </li>\n       <li class=\"cat-item cat-item-17\">\n        <a href=\"http://dgquftlj2h3rhbalvz6o6s7ilg32bg763eqjyb76wlv4w2cndfzzrdid.onion/the/\">\n         The\n        </a>\n       </li>\n       <li class=\"cat-item cat-item-17\">\n        <a href=\"http://dgquftlj2h3rhbalvz6o6s7ilg32bg763eqjyb76wlv4w2cndfzzrdid.onion/wifi/\">\n         Wifi\n        </a>\n       </li>\n       <li class=\"cat-item cat-item-17\">\n        <a href=\"http://dgquftlj2h3rhbalvz6o6s7ilg32bg763eqjyb76wlv4w2cndfzzrdid.onion/with/\">\n         With\n        </a>\n       </li>\n      </ul>\n     </div>\n     <div class=\"widget widget_recent_comments\" id=\"recent-comments-2\">\n      <h3 class=\"widget-title\">\n       Свежие комментарии\n      </h3>\n      <ul id=\"recentcomments\">\n       <li class=\"recentcomments\">\n        <span class=\"comment-author-link\">\n         Jukree\n        </span>\n        к записи\n        <a href=\"http://dgquftlj2h3rhbalvz6o6s7ilg32bg763eqjyb76wlv4w2cndfzzrdid.onion/how/how-to-paint-laminate-furniture.html#comment-1\">\n         How to paint laminate furniture\n        </a>\n       </li>\n       <li class=\"recentcomments\">\n        <span class=\"comment-author-link\">\n         Meztikree\n        </span>\n        к записи\n        <a href=\"http://dgquftlj2h3rhbalvz6o6s7ilg32bg763eqjyb76wlv4w2cndfzzrdid.onion/how/how-to-paint-laminate-furniture.html#comment-1\">\n         How to paint laminate furniture\n        </a>\n       </li>\n       <li class=\"recentcomments\">\n        <span class=\"comment-author-link\">\n         Dagar\n        </span>\n        к записи\n        <a href=\"http://dgquftlj2h3rhbalvz6o6s7ilg32bg763eqjyb76wlv4w2cndfzzrdid.onion/how/how-to-paint-laminate-furniture.html#comment-1\">\n         How to paint laminate furniture\n        </a>\n       </li>\n       <li class=\"recentcomments\">\n        <span class=\"comment-author-link\">\n         Kagahn\n        </span>\n        к записи\n        <a href=\"http://dgquftlj2h3rhbalvz6o6s7ilg32bg763eqjyb76wlv4w2cndfzzrdid.onion/how/how-to-paint-laminate-furniture.html#comment-1\">\n         How to paint laminate furniture\n        </a>\n       </li>\n       <li class=\"recentcomments\">\n        <span class=\"comment-author-link\">\n         Gur\n        </span>\n        к записи\n        <a href=\"http://dgquftlj2h3rhbalvz6o6s7ilg32bg763eqjyb76wlv4w2cndfzzrdid.onion/how/how-to-paint-laminate-furniture.html#comment-1\">\n         How to paint laminate furniture\n        </a>\n       </li>\n      </ul>\n     </div>\n     <div class=\"widget widget_meta\" id=\"meta-2\">\n      <h3 class=\"widget-title\">\n       Мета\n      </h3>\n      <ul>\n       <li>\n        <a href=\"http://dgquftlj2h3rhbalvz6o6s7ilg32bg763eqjyb76wlv4w2cndfzzrdid.onion\">\n         Войти\n        </a>\n       </li>\n       <li>\n        <a href=\"http://dgquftlj2h3rhbalvz6o6s7ilg32bg763eqjyb76wlv4w2cndfzzrdid.onion/rss.xml\">\n         Лента записей\n        </a>\n       </li>\n       <li>\n        <a href=\"http://dgquftlj2h3rhbalvz6o6s7ilg32bg763eqjyb76wlv4w2cndfzzrdid.onion/rss.xml\">\n         Лента комментариев\n        </a>\n       </li>\n       <li>\n        <a href=\"#\">\n         WordPress.org\n        </a>\n       </li>\n      </ul>\n     </div>\n     <div class=\"widget widget_recent_entries\" id=\"recent-posts-2\">\n      <h3 class=\"widget-title\">\n       Свежие записи\n      </h3>\n      <ul>\n       <li>\n        <a href=\"http://dgquftlj2h3rhbalvz6o6s7ilg32bg763eqjyb76wlv4w2cndfzzrdid.onion/codes/governor-of-poker-3-cheat-codes.html\">\n         Governor of poker 3 cheat codes\n        </a>\n       </li>\n       <li>\n        <a href=\"http://dgquftlj2h3rhbalvz6o6s7ilg32bg763eqjyb76wlv4w2cndfzzrdid.onion/pokemon/pokemon-glazed-1.html\">\n         Pokemon glazed\n        </a>\n       </li>\n       <li>\n        <a href=\"http://dgquftlj2h3rhbalvz6o6s7ilg32bg763eqjyb76wlv4w2cndfzzrdid.onion/minecraft/block-esp-minecraft.html\">\n         Block esp minecraft\n        </a>\n       </li>\n       <li>\n        <a href=\"http://dgquftlj2h3rhbalvz6o6s7ilg32bg763eqjyb76wlv4w2cndfzzrdid.onion/kali/how-to-start-metasploit-in-kali-linux.html\">\n         How to start metasploit in kali linux\n        </a>\n       </li>\n       <li>\n        <a href=\"http://dgquftlj2h3rhbalvz6o6s7ilg32bg763eqjyb76wlv4w2cndfzzrdid.onion/ios/pubg-mobile-hack-ios-no-recoil.html\">\n         Pubg mobile hack ios no recoil\n        </a>\n       </li>\n      </ul>\n     </div>\n    </div>\n    <div id=\"footer-widget-wrapper-left\">\n    </div>\n   </div>\n   <div id=\"footer-credits-wrapper\">\n    <div id=\"site-footer\">\n     2020 tarva 3-drawer chest. All rights reserved.\n    </div>\n   </div>\n  </footer>\n  <script src=\"http://dgquftlj2h3rhbalvz6o6s7ilg32bg763eqjyb76wlv4w2cndfzzrdid.onion/wp-includes/js/wp-embed.min.js?ver=5.3\">\n  </script>\n </body>\n</html>\n"
}